rss_reader/__init__.py
rss_reader/action_functions.py
rss_reader/caching_functions.py
rss_reader/conversion_functions.py
rss_reader/exceptions.py
rss_reader/models.py
rss_reader/rss_reader.py
rss_reader/validation_functions.py
rss_reader_Anna_Gonchar-4.2.dist-info/METADATA
rss_reader_Anna_Gonchar-4.2.dist-info/WHEEL
rss_reader_Anna_Gonchar-4.2.dist-info/entry_points.txt
rss_reader_Anna_Gonchar-4.2.dist-info/top_level.txt
rss_reader_Anna_Gonchar-4.2.dist-info/RECORD
