Metadata-Version: 2.1
Name: rss-reader-Anna-Gonchar
Version: 4.2
Summary: RSS reader - simple command-line utility.
Home-page: https://github.com/AnnaPotter/FinalTaskRssParser
Author: Anna Gonchar
Author-email: raphaelkyzy@gmail.com
License: UNKNOWN
Platform: UNKNOWN
Classifier: Programming Language :: Python :: 3.8
Classifier: Operating System :: OS Independent
Requires-Python: >=3.8
Requires-Dist: feedparser
Requires-Dist: requests
Requires-Dist: beautifulsoup4 (==4.8.1)
Requires-Dist: fpdf
Requires-Dist: dominate
